{
  "timestamp": "2025-08-25T00:40:57.269Z",
  "status": "completed",
  "spacesCreated": {},
  "modulesPopulated": {
    "contact": {
      "status": "failed",
      "error": "Request failed with status code 500",
      "spaceId": 26
    },
    "product": {
      "status": "failed",
      "error": "Request failed with status code 500",
      "spaceId": 27
    },
    "invoice": {
      "status": "already_populated",
      "recordCount": 6,
      "spaceId": 27
    },
    "event": {
      "status": "failed",
      "error": "Request failed with status code 500",
      "spaceId": 27
    },
    "note": {
      "status": "failed",
      "error": "Request failed with status code 500",
      "spaceId": 27
    },
    "business-order": {
      "status": "failed",
      "error": "Request failed with status code 500",
      "spaceId": 29
    },
    "business-offer": {
      "status": "failed",
      "error": "Request failed with status code 500",
      "spaceId": 29
    },
    "form": {
      "status": "failed",
      "error": "Request failed with status code 500",
      "spaceId": 27
    },
    "business-case": {
      "status": "failed",
      "error": "Request failed with status code 500",
      "spaceId": 29
    },
    "business-contract": {
      "status": "failed",
      "error": "Request failed with status code 500",
      "spaceId": 29
    },
    "todo": {
      "status": "failed",
      "error": "Request failed with status code 500",
      "spaceId": 27
    },
    "project": {
      "status": "failed",
      "error": "Request failed with status code 404",
      "spaceId": 31
    },
    "work": {
      "status": "failed",
      "error": "Request failed with status code 500",
      "spaceId": 27
    },
    "activities": {
      "status": "already_populated",
      "recordCount": 2,
      "spaceId": 27
    },
    "team": {
      "status": "already_populated",
      "recordCount": 2,
      "spaceId": 27
    },
    "user": {
      "status": "already_populated",
      "recordCount": 1,
      "spaceId": 27
    },
    "category": {
      "status": "already_populated",
      "recordCount": 2,
      "spaceId": 27
    },
    "submission": {
      "status": "failed",
      "error": "Request failed with status code 500",
      "spaceId": 27
    },
    "purchase": {
      "status": "failed",
      "error": "Request failed with status code 500",
      "spaceId": 27
    },
    "stock-request": {
      "status": "already_populated",
      "recordCount": 1,
      "spaceId": 27
    },
    "stock-reservation": {
      "status": "populating",
      "records": [
        {
          "data": {
            "spaceId": 27,
            "statusSystemId": 1,
            "name": "Stock-reservation Record 1",
            "description": "Sample stock-reservation record"
          },
          "status": "failed",
          "error": "Request failed with status code 400"
        },
        {
          "data": {
            "spaceId": 27,
            "statusSystemId": 1,
            "name": "Stock-reservation Record 2",
            "description": "Sample stock-reservation record"
          },
          "status": "failed",
          "error": "Request failed with status code 400"
        }
      ],
      "spaceId": 27,
      "summary": {
        "total": 2,
        "successful": 0,
        "failed": 2
      }
    },
    "stock-inventory": {
      "status": "failed",
      "error": "Request failed with status code 500",
      "spaceId": 27
    },
    "stock-item": {
      "status": "failed",
      "error": "Request failed with status code 500",
      "spaceId": 27
    },
    "address": {
      "status": "already_populated",
      "recordCount": 2,
      "spaceId": 27
    },
    "page": {
      "status": "failed",
      "error": "Request failed with status code 500",
      "spaceId": 27
    },
    "resource": {
      "status": "already_populated",
      "recordCount": 3,
      "spaceId": 27
    },
    "integration": {
      "status": "populating",
      "records": [
        {
          "data": {
            "spaceId": 27,
            "statusSystemId": 1,
            "name": "Integration Record 1",
            "description": "Sample integration record"
          },
          "status": "failed",
          "error": "Request failed with status code 400"
        },
        {
          "data": {
            "spaceId": 27,
            "statusSystemId": 1,
            "name": "Integration Record 2",
            "description": "Sample integration record"
          },
          "status": "failed",
          "error": "Request failed with status code 400"
        }
      ],
      "spaceId": 27,
      "summary": {
        "total": 2,
        "successful": 0,
        "failed": 2
      }
    },
    "chart": {
      "status": "failed",
      "error": "Request failed with status code 500",
      "spaceId": 27
    },
    "custom-info": {
      "status": "failed",
      "error": "Request failed with status code 404",
      "spaceId": 27
    },
    "custom-module-item": {
      "status": "failed",
      "error": "Request failed with status code 500",
      "spaceId": 27
    },
    "automatization": {
      "status": "failed",
      "error": "Request failed with status code 404",
      "spaceId": 27
    },
    "import": {
      "status": "populating",
      "records": [
        {
          "data": {
            "spaceId": 27,
            "statusSystemId": 1,
            "name": "Import Record 1",
            "description": "Sample import record"
          },
          "status": "failed",
          "error": "Request failed with status code 400"
        },
        {
          "data": {
            "spaceId": 27,
            "statusSystemId": 1,
            "name": "Import Record 2",
            "description": "Sample import record"
          },
          "status": "failed",
          "error": "Request failed with status code 400"
        }
      ],
      "spaceId": 27,
      "summary": {
        "total": 2,
        "successful": 0,
        "failed": 2
      }
    },
    "payment": {
      "status": "populating",
      "records": [
        {
          "data": {
            "spaceId": 27,
            "statusSystemId": 1,
            "name": "Payment Record 1",
            "description": "Sample payment record"
          },
          "status": "failed",
          "error": "Request failed with status code 400"
        },
        {
          "data": {
            "spaceId": 27,
            "statusSystemId": 1,
            "name": "Payment Record 2",
            "description": "Sample payment record"
          },
          "status": "failed",
          "error": "Request failed with status code 400"
        }
      ],
      "spaceId": 27,
      "summary": {
        "total": 2,
        "successful": 0,
        "failed": 2
      }
    }
  },
  "summary": {
    "totalSpaces": 0,
    "createdSpaces": 0,
    "totalModules": 0,
    "successfulModules": 8,
    "totalRecords": 0,
    "successfulRecords": 19
  }
}