{
  "phase": "build",
  "objective": "Implement secure multi-user AI agent architecture",
  "tasks": [
    {
      "id": "BUILD-001",
      "title": "Implement Chat Proxy Architecture",
      "description": "Create secure proxy to hide n8n webhook URLs and credentials",
      "priority": "HIGH",
      "effort": "2 days",
      "dependencies": [],
      "deliverables": [
        "Secure chat proxy endpoint",
        "Hidden webhook URL configuration",
        "Server-side customer ID injection"
      ],
      "videoReference": "Strategy 1: Chat Proxy"
    },
    {
      "id": "BUILD-002",
      "title": "Implement JWT Origin Verification",
      "description": "Add JWT-based authentication to verify request origins",
      "priority": "HIGH",
      "effort": "1 day",
      "dependencies": [
        "BUILD-001"
      ],
      "deliverables": [
        "JWT generation and verification functions",
        "Short-lived token implementation",
        "Origin validation middleware"
      ],
      "videoReference": "Strategy 2: Verify Origin"
    },
    {
      "id": "BUILD-003",
      "title": "Implement Database Row-Level Security",
      "description": "Add RLS policies to ensure data isolation between customers",
      "priority": "HIGH",
      "effort": "2 days",
      "dependencies": [],
      "deliverables": [
        "Supabase RLS policies",
        "Customer data isolation rules",
        "Storage bucket security policies"
      ],
      "videoReference": "Strategy 3: Lock Down Supabase"
    },
    {
      "id": "BUILD-004",
      "title": "Implement Multi-Factor Authentication",
      "description": "Add step-up authentication for sensitive operations",
      "priority": "MEDIUM",
      "effort": "3 days",
      "dependencies": [
        "BUILD-002"
      ],
      "deliverables": [
        "SMS-based MFA system",
        "Sensitive operation detection",
        "MFA verification workflow"
      ],
      "videoReference": "Strategy 4: MFA"
    },
    {
      "id": "BUILD-005",
      "title": "Implement Principle of Least Privilege",
      "description": "Create specific database users with minimal required permissions",
      "priority": "HIGH",
      "effort": "1 day",
      "dependencies": [
        "BUILD-003"
      ],
      "deliverables": [
        "Specific database user accounts",
        "Permission-based access control",
        "API key restrictions"
      ],
      "videoReference": "Strategy 5: PLP"
    },
    {
      "id": "BUILD-006",
      "title": "Implement Database-Level Security",
      "description": "Use secure identity provider with access tokens",
      "priority": "MEDIUM",
      "effort": "2 days",
      "dependencies": [
        "BUILD-002",
        "BUILD-005"
      ],
      "deliverables": [
        "Identity provider integration",
        "Access token validation",
        "Database-level security policies"
      ],
      "videoReference": "Strategy 6: DB RLS"
    },
    {
      "id": "BUILD-007",
      "title": "Implement Additional Security Measures",
      "description": "Add rate limiting, monitoring, and input validation",
      "priority": "MEDIUM",
      "effort": "2 days",
      "dependencies": [
        "BUILD-001"
      ],
      "deliverables": [
        "Rate limiting system",
        "Input validation and sanitization",
        "Security monitoring and alerting"
      ],
      "videoReference": "Strategy 7: Other Techniques"
    }
  ],
  "successCriteria": [
    "All 7 security strategies implemented",
    "Zero data leakage between customers",
    "Comprehensive audit logging",
    "Real-time security monitoring",
    "Compliance with data protection regulations"
  ]
}