{
  "timestamp": "2025-08-17T19:20:56.622Z",
  "fixes": {
    "mcpWebhook": {
      "status": "failed",
      "error": "Request failed with status code 400"
    },
    "bmadAutomation": {
      "status": "failed",
      "error": "Request failed with status code 400"
    },
    "taskManagement": {
      "status": "failed",
      "error": "Request failed with status code 400"
    },
    "knowledgebase": {
      "status": "error",
      "error": "Request failed with status code 404"
    },
    "mcpserverwebhook": {
      "status": "error",
      "error": "Request failed with status code 404"
    },
    "bmadautomation": {
      "status": "error",
      "error": "Request failed with status code 404"
    },
    "taskmanagement": {
      "status": "error",
      "error": "Request failed with status code 404"
    }
  },
  "status": "completed"
}